mcp_server_monday/__init__.py
mcp_server_monday/board.py
mcp_server_monday/constants.py
mcp_server_monday/fastmcp_server.py
mcp_server_monday/item.py
mseep_mcp_server_monday-0.3.1.dist-info/licenses/LICENSE
mseep_mcp_server_monday-0.3.1.dist-info/METADATA
mseep_mcp_server_monday-0.3.1.dist-info/WHEEL
mseep_mcp_server_monday-0.3.1.dist-info/entry_points.txt
mseep_mcp_server_monday-0.3.1.dist-info/top_level.txt
mseep_mcp_server_monday-0.3.1.dist-info/RECORD
